affapy/__init__.py
affapy/aa.py
affapy/error.py
affapy/ia.py
affapy/precision.py
affapy-0.1.dist-info/LICENSE
affapy-0.1.dist-info/METADATA
affapy-0.1.dist-info/WHEEL
affapy-0.1.dist-info/top_level.txt
affapy-0.1.dist-info/RECORD
