Metadata-Version: 2.1
Name: affapy
Version: 0.1
Summary: A Python library for multiprecision Affine Arithmetic
Home-page: https://gitlab.lip6.fr/hilaire/affapy
Author: Quentin DESCHAMPS
Author-email: quentin.deschamps@etu.sorbonne-universite.fr
License: UNKNOWN
Platform: UNKNOWN
Classifier: Programming Language :: Python :: 3
Classifier: License :: OSI Approved :: GNU General Public License v3 (GPLv3)
Classifier: Operating System :: OS Independent
Requires-Python: >=3.5
Requires-Dist: mpmath
